AudioCodes/__init__.py
AudioCodes/acsbc_api.py
MrLou_AudioCodes/__init__.py
MrLou_AudioCodes/acsbc_api.py
MrLou_AudioCodes-0.3.0.dist-info/METADATA
MrLou_AudioCodes-0.3.0.dist-info/WHEEL
MrLou_AudioCodes-0.3.0.dist-info/top_level.txt
MrLou_AudioCodes-0.3.0.dist-info/RECORD
