Metadata-Version: 2.1
Name: MrLou-AudioCodes
Version: 0.3.0
Summary: A module for MrLou_AudioCodes API
Home-page: https://github.com/lpdescamps/AudioCodes
Author: Louis-Philippe Descamps
Author-email: me@lpdne.eu
License: UNKNOWN
Platform: UNKNOWN
Classifier: Programming Language :: Python :: 3
Classifier: License :: OSI Approved :: MIT License
Classifier: Operating System :: OS Independent
Requires-Python: >=3.6
